aenoxcord/__init__.py
aenoxcord/blacklist.py
aenoxcord/bot.py
aenoxcord/components.py
aenoxcord/emb.py
aenoxcord/enums.py
aenoxcord/errors.py
aenoxcord/i18n.py
aenoxcord/logs.py
aenoxcord/times.py
aenoxcord/utils.py
aenoxcord/cogs/blacklist.py
aenoxcord/cogs/help.py
aenoxcord/cogs/status_changer.py
aenoxcord/cogs/dpy/blacklist_setup.py
aenoxcord/cogs/dpy/help_setup.py
aenoxcord/cogs/dpy/status_changer_setup.py
aenoxcord/cogs/pyc/blacklist_setup.py
aenoxcord/cogs/pyc/help_setup.py
aenoxcord/cogs/pyc/status_changer_setup.py
aenoxcord/internal/__init__.py
aenoxcord/internal/colors.py
aenoxcord/internal/config.py
aenoxcord/internal/embed_templates.py
aenoxcord/internal/ready_style.py
aenoxcord/internal/translation.py
aenoxcord/internal/dc/__init__.py
aenoxcord/internal/dc/dc_imports.py
aenoxcord/internal/language/de.json
aenoxcord/internal/language/en.json
aenoxcord/internal/language/languages.py
aenoxcord/sql/__init__.py
aenoxcord/sql/fake_pg.py
aenoxcord/sql/postgresql.py
aenoxcord/sql/sqlite.py
aenoxcord-0.0.1.dist-info/licenses/LICENSE
aenoxcord-0.0.1.dist-info/METADATA
aenoxcord-0.0.1.dist-info/WHEEL
aenoxcord-0.0.1.dist-info/top_level.txt
aenoxcord-0.0.1.dist-info/RECORD
